huaweicloudsdkhilens/__init__.py
huaweicloudsdkhilens/v1/__init__.py
huaweicloudsdkhilens/v1/hilens_async_client.py
huaweicloudsdkhilens/v1/hilens_client.py
huaweicloudsdkhilens/v1/model/__init__.py
huaweicloudsdkhilens/v1/model/get_device_alarm_array_object.py
huaweicloudsdkhilens/v1/model/get_devices_list_array_object.py
huaweicloudsdkhilens/v1/model/list_device_alarms_request.py
huaweicloudsdkhilens/v1/model/list_device_alarms_response.py
huaweicloudsdkhilens/v1/model/list_devices_request.py
huaweicloudsdkhilens/v1/model/list_devices_response.py
huaweicloudsdkhilens/v1/region/__init__.py
huaweicloudsdkhilens/v1/region/hilens_region.py
huaweicloudsdkhilens/v3/__init__.py
huaweicloudsdkhilens/v3/hilens_async_client.py
huaweicloudsdkhilens/v3/hilens_client.py
huaweicloudsdkhilens/v3/model/__init__.py
huaweicloudsdkhilens/v3/model/activate_node_request_body.py
huaweicloudsdkhilens/v3/model/activate_record_records.py
huaweicloudsdkhilens/v3/model/add_deployment_nodes_request.py
huaweicloudsdkhilens/v3/model/add_deployment_nodes_response.py
huaweicloudsdkhilens/v3/model/app_def.py
huaweicloudsdkhilens/v3/model/batch_create_node_tags_request.py
huaweicloudsdkhilens/v3/model/batch_create_node_tags_response.py
huaweicloudsdkhilens/v3/model/config.py
huaweicloudsdkhilens/v3/model/config_map.py
huaweicloudsdkhilens/v3/model/config_map_id.py
huaweicloudsdkhilens/v3/model/config_map_model_box_dto.py
huaweicloudsdkhilens/v3/model/configs_map.py
huaweicloudsdkhilens/v3/model/create_config_map_request.py
huaweicloudsdkhilens/v3/model/create_config_map_response.py
huaweicloudsdkhilens/v3/model/create_deployment_request.py
huaweicloudsdkhilens/v3/model/create_deployment_response.py
huaweicloudsdkhilens/v3/model/create_node_request.py
huaweicloudsdkhilens/v3/model/create_node_response.py
huaweicloudsdkhilens/v3/model/create_order_form_request.py
huaweicloudsdkhilens/v3/model/create_order_form_response.py
huaweicloudsdkhilens/v3/model/create_resource_tags_request.py
huaweicloudsdkhilens-3.1.184.dist-info/METADATA
huaweicloudsdkhilens-3.1.184.dist-info/WHEEL
huaweicloudsdkhilens-3.1.184.dist-info/licenses/LICENSE
huaweicloudsdkhilens-3.1.184.dist-info/RECORD
